flake8_tuple_trailing_commas.py
flake8_tuple_trailing_commas-0.1.3.dist-info/LICENSE
flake8_tuple_trailing_commas-0.1.3.dist-info/METADATA
flake8_tuple_trailing_commas-0.1.3.dist-info/WHEEL
flake8_tuple_trailing_commas-0.1.3.dist-info/entry_points.txt
flake8_tuple_trailing_commas-0.1.3.dist-info/top_level.txt
flake8_tuple_trailing_commas-0.1.3.dist-info/RECORD
