Metadata-Version: 2.1
Name: flake8-tuple-trailing-commas
Version: 0.1.3
Summary: flake8 plugin for enforcing few rules
Home-page: https://github.com/davemus/flake8-custom-trailing-commas
Author: Drozdov David
Author-email: drozdovud@gmail.com
License: UNKNOWN
Platform: UNKNOWN
Classifier: Programming Language :: Python :: 3
Classifier: License :: OSI Approved :: MIT License
Requires-Dist: flake8 (>=3.7)
Requires-Dist: importlib-metadata (>=0.9) ; python_version <= "3.8"
